odoo/addons/account_move_line_accounting_description_sale/README.rst
odoo/addons/account_move_line_accounting_description_sale/__init__.py
odoo/addons/account_move_line_accounting_description_sale/__manifest__.py
odoo/addons/account_move_line_accounting_description_sale/i18n/account_move_line_accounting_description_sale.pot
odoo/addons/account_move_line_accounting_description_sale/i18n/es.po
odoo/addons/account_move_line_accounting_description_sale/i18n/it.po
odoo/addons/account_move_line_accounting_description_sale/models/__init__.py
odoo/addons/account_move_line_accounting_description_sale/models/sale_order.py
odoo/addons/account_move_line_accounting_description_sale/readme/CONTRIBUTORS.rst
odoo/addons/account_move_line_accounting_description_sale/readme/DESCRIPTION.rst
odoo/addons/account_move_line_accounting_description_sale/static/description/icon.png
odoo/addons/account_move_line_accounting_description_sale/static/description/index.html
odoo/addons/account_move_line_accounting_description_sale/tests/__init__.py
odoo/addons/account_move_line_accounting_description_sale/tests/test_sale_description.py
odoo14_addon_account_move_line_accounting_description_sale-14.0.1.0.1.dev10.dist-info/METADATA
odoo14_addon_account_move_line_accounting_description_sale-14.0.1.0.1.dev10.dist-info/WHEEL
odoo14_addon_account_move_line_accounting_description_sale-14.0.1.0.1.dev10.dist-info/top_level.txt
odoo14_addon_account_move_line_accounting_description_sale-14.0.1.0.1.dev10.dist-info/RECORD
